setup.py
ypconfig/__init__.py
ypconfig/cli.py
ypconfig/config.py
ypconfig/netlink.py
ypconfig.egg-info/PKG-INFO
ypconfig.egg-info/SOURCES.txt
ypconfig.egg-info/dependency_links.txt
ypconfig.egg-info/entry_points.txt
ypconfig.egg-info/requires.txt
ypconfig.egg-info/top_level.txt